connect/__init__.py
connect/config.py
connect/exceptions.py
connect/logger/__init__.py
connect/logger/config.json
connect/logger/logger.py
connect/models/__init__.py
connect/models/activation.py
connect/models/activation_template_response.py
connect/models/activation_tile_response.py
connect/models/agreement.py
connect/models/agreement_stats.py
connect/models/anniversary.py
connect/models/asset.py
connect/models/asset_request.py
connect/models/attributes.py
connect/models/base.py
connect/models/billing.py
connect/models/billing_request.py
connect/models/commitment.py
connect/models/company.py
connect/models/configuration.py
connect/models/connection.py
connect/models/constraints.py
connect/models/contact.py
connect/models/contact_info.py
connect/models/contract.py
connect/models/conversation.py
connect/models/conversation_message.py
connect/models/country.py
connect/models/customer_ui_settings.py
connect/models/document.py
connect/models/download_link.py
connect/models/event.py
connect/models/events.py
connect/models/exception.py
connect/models/ext_id_hub.py
connect/models/fulfillment.py
connect/models/hub.py
connect/models/hub_instance.py
connect/models/hub_stats.py
connect/models/item.py
connect/models/last_request.py
connect/models/marketplace.py
connect/models/param.py
connect/models/period.py
connect/models/phone_number.py
connect/models/product.py
connect/models/product_category.py
connect/models/product_configuration.py
connect/models/product_configuration_parameter.py
connect/models/product_family.py
connect/models/product_stats.py
connect/models/product_stats_info.py
connect/models/recurring_asset.py
connect/models/renewal.py
connect/models/schemas.py
connect/models/server_error_response.py
connect/models/stat.py
connect/models/stats.py
connect/models/template.py
connect/models/tier_account.py
connect/models/tier_account_request.py
connect/models/tier_accounts.py
connect/models/tier_config.py
connect/models/tier_config_request.py
connect/models/ui.py
connect_sdk-22.0.dist-info/LICENSE
connect_sdk-22.0.dist-info/METADATA
connect_sdk-22.0.dist-info/WHEEL
connect_sdk-22.0.dist-info/top_level.txt
connect_sdk-22.0.dist-info/RECORD
