Metadata-Version: 2.1
Name: connect-sdk
Version: 22.0
Summary: Connect Python SDK
Home-page: https://github.com/ingrammicro/connect-python-sdk
Author: CloudBlue Connect
License: Apache Software License
Keywords: sdk connect connect automation
Platform: UNKNOWN
Classifier: Development Status :: 5 - Production/Stable
Classifier: Intended Audience :: Developers
Classifier: Topic :: Software Development :: Libraries :: Python Modules
Classifier: License :: OSI Approved :: Apache Software License
Classifier: Programming Language :: Python
Classifier: Programming Language :: Python :: 2.7
Classifier: Programming Language :: Python :: 3.4
Classifier: Programming Language :: Python :: 3.5
Classifier: Programming Language :: Python :: 3.6
Classifier: Programming Language :: Python :: 3.7
Classifier: Operating System :: OS Independent
Classifier: Operating System :: POSIX
Classifier: Operating System :: MacOS
Classifier: Operating System :: Unix
Requires-Dist: deprecation (==2.0.6)
Requires-Dist: marshmallow (==2.18.0)
Requires-Dist: openpyxl (>=2.5.14)
Requires-Dist: requests (==2.21.0)
Requires-Dist: six (==1.12.0)
Requires-Dist: pathlib (==1.0.1)
